adhawkapi/frontend_ble/__init__.py
adhawkapi/frontend_ble/blecom.py
adhawkapi/frontend_ble/frontend_api.py
adhawk_ble-6.1.dist-info/LICENSE.md
adhawk_ble-6.1.dist-info/METADATA
adhawk_ble-6.1.dist-info/WHEEL
adhawk_ble-6.1.dist-info/top_level.txt
adhawk_ble-6.1.dist-info/RECORD
